fensterbrief
templates
