Metadata-Version: 1.1
Name: fensterbrief
Version: 0.0.16
Summary: Fensterbrief is a python script for working with letters based on LaTeX and Markdown.
Home-page: https://github.com/nitram2342/fensterbrief
Author: Martin Schobert
Author-email: martin@weltregierung.de
License: BSD
Keywords: latex letters office productivity
Platform: UNKNOWN
Classifier: Development Status :: 3 - Alpha
Classifier: Intended Audience :: End Users/Desktop
Classifier: Topic :: Office/Business
Classifier: Topic :: Text Processing :: Markup :: LaTeX
Classifier: Topic :: Utilities
Classifier: Topic :: Communications :: Fax
Classifier: License :: OSI Approved :: BSD License
Classifier: Programming Language :: Python :: 3
